aryth/__init__.py
aryth/bound/__init__.py
aryth/bound/entries/__init__.py
aryth/bound/entries/indicator.py
aryth/bound/matrix/__init__.py
aryth/bound/matrix/bound.py
aryth/bound/matrix/duobound.py
aryth/bound/matrix/indicator.py
aryth/bound/matrix/solebound.py
aryth/bound/vector/__init__.py
aryth/bound/vector/bound.py
aryth/bound/vector/duobound.py
aryth/bound/vector/indicator.py
aryth/bound/vector/solebound.py
aryth/comparison/__init__.py
aryth/constraint/__init__.py
aryth/enum/__init__.py
aryth/math/__init__.py
aryth/stat/__init__.py
aryth/structs/__init__.py
aryth/structs/leap/__init__.py
aryth/structs/select/__init__.py
aryth/structs/tag_list/__init__.py
aryth-0.0.12.dist-info/WHEEL
aryth-0.0.12.dist-info/METADATA
aryth-0.0.12.dist-info/RECORD
